fobi/__init__.py
fobi/admin.py
fobi/app.py
fobi/apps.py
fobi/base.py
fobi/conf.py
fobi/constants.py
fobi/context_processors.py
fobi/data_structures.py
fobi/decorators.py
fobi/defaults.py
fobi/discover.py
fobi/dynamic.py
fobi/exceptions.py
fobi/form_importers.py
fobi/form_utils.py
fobi/forms.py
fobi/helpers.py
fobi/models.py
fobi/pip_helpers.py
fobi/settings.py
fobi/utils.py
fobi/validators.py
fobi/widgets.py
fobi/contrib/__init__.py
fobi/contrib/apps/__init__.py
fobi/contrib/apps/djangocms_integration/__init__.py
fobi/contrib/apps/djangocms_integration/apps.py
fobi/contrib/apps/djangocms_integration/cms_plugins.py
fobi/contrib/apps/djangocms_integration/cms_version.py
fobi/contrib/apps/djangocms_integration/conf.py
fobi/contrib/apps/djangocms_integration/defaults.py
fobi/contrib/apps/djangocms_integration/helpers.py
fobi/contrib/apps/djangocms_integration/models.py
fobi/contrib/apps/djangocms_integration/settings.py
fobi/contrib/apps/djangocms_integration/migrations/0001_initial.py
fobi/contrib/apps/djangocms_integration/migrations/__init__.py
fobi/contrib/apps/djangocms_integration/templates/djangocms_integration/login_required.html
fobi/contrib/apps/djangocms_integration/templates/djangocms_integration/widget.html
fobi/contrib/apps/drf_integration/__init__.py
fobi/contrib/apps/drf_integration/apps.py
fobi/contrib/apps/drf_integration/base.py
fobi/contrib/apps/drf_integration/dynamic.py
fobi/contrib/apps/drf_integration/fields.py
fobi/contrib/apps/drf_integration/helpers.py
fobi/contrib/apps/drf_integration/metadata.py
fobi/contrib/apps/drf_integration/serializers.py
fobi/contrib/apps/drf_integration/urls.py
fobi/contrib/apps/drf_integration/utils.py
fobi/contrib/apps/drf_integration/views.py
fobi/contrib/apps/drf_integration/form_elements/__init__.py
fobi/contrib/apps/drf_integration/form_elements/content/__init__.py
fobi/contrib/apps/drf_integration/form_elements/content/content_image/__init__.py
django_fobi-0.19.9.dist-info/LICENSE_GPL2.0.txt
django_fobi-0.19.9.dist-info/METADATA
django_fobi-0.19.9.dist-info/WHEEL
django_fobi-0.19.9.dist-info/top_level.txt
django_fobi-0.19.9.dist-info/RECORD
