Metadata-Version: 2.1
Name: django-fobi
Version: 0.19.9
Summary: Form generator/builder application for Django done right: customisable, modular, user- and developer- friendly.
Home-page: https://github.com/barseghyanartur/django-fobi/
Author: Artur Barseghyan
Author-email: artur.barseghyan@gmail.com
License: GPL-2.0-only OR LGPL-2.1-or-later
Project-URL: Bug Tracker, https://github.com/barseghyanartur/django-fobi/issues
Project-URL: Documentation, https://django-fobi.readthedocs.io/
Project-URL: Source Code, https://github.com/barseghyanartur/django-fobi
Project-URL: Changelog, https://django-fobi.readthedocs.io/en/latest/changelog.html
Keywords: django,form generator,form builder,visual form designer,user generated forms
Classifier: Programming Language :: Python :: 3
Classifier: Programming Language :: Python :: 3.7
Classifier: Programming Language :: Python :: 3.8
Classifier: Programming Language :: Python :: 3.9
Classifier: Programming Language :: Python :: 3.10
Classifier: Programming Language :: Python :: 3.11
Classifier: Environment :: Web Environment
Classifier: License :: OSI Approved :: GNU General Public License v2 (GPLv2)
Classifier: License :: OSI Approved :: GNU Lesser General Public License v2 or later (LGPLv2+)
Classifier: Framework :: Django
Classifier: Framework :: Django :: 2.2
Classifier: Framework :: Django :: 3.0
Classifier: Framework :: Django :: 3.1
Classifier: Framework :: Django :: 3.2
Classifier: Framework :: Django :: 4.0
Classifier: Framework :: Django :: 4.1
Classifier: Intended Audience :: Developers
Classifier: Operating System :: OS Independent
Classifier: Development Status :: 4 - Beta
License-File: LICENSE_GPL2.0.txt
Requires-Dist: bleach
Requires-Dist: django-autoslug (>=1.9.4)
Requires-Dist: django-formtools (>=2.0)
Requires-Dist: django-nine (>=0.2.3)
Requires-Dist: django-nonefield (>=0.1)
Requires-Dist: Pillow (>=2.0.0)
Requires-Dist: requests (>=1.0.0)
Requires-Dist: six (>=1.9)
Requires-Dist: Unidecode (>=0.04.1)
Requires-Dist: vishap (<2.0,>=0.1.5)
Requires-Dist: easy-thumbnails (>=2.4.1)
